simupy/__init__.py
simupy/array.py
simupy/block_diagram.py
simupy/codegen-LOCAL.py
simupy/codegen.py
simupy/discontinuities.py
simupy/matrices.py
simupy/simulation.py
simupy/version.py
simupy/systems/__init__.py
simupy/systems/symbolic.py
simupy/utils/__init__.py
simupy/utils/symbolic.py
simupy/utils/test.py
simupy-1.1.2.dist-info/LICENSE
simupy-1.1.2.dist-info/METADATA
simupy-1.1.2.dist-info/WHEEL
simupy-1.1.2.dist-info/top_level.txt
simupy-1.1.2.dist-info/RECORD
