Metadata-Version: 2.1
Name: simupy
Version: 1.1.2
Summary: A framework for modeling and simulating dynamical systems.
Home-page: https://github.com/simupy/simupy
Author: Benjamin Margolis
Author-email: ben@sixpearls.com
License: BSD 2-clause "Simplified" License
Classifier: License :: OSI Approved :: BSD License
Classifier: Programming Language :: Python :: 3
Classifier: Intended Audience :: Education
Classifier: Intended Audience :: Science/Research
Classifier: Operating System :: OS Independent
Classifier: Topic :: Scientific/Engineering :: Physics
Classifier: Topic :: Scientific/Engineering :: Mathematics
Requires-Python: >=3
License-File: LICENSE
Requires-Dist: numpy (>=1.11.3)
Requires-Dist: scipy (>=0.18.1)
Provides-Extra: doc
Requires-Dist: sphinx (>=1.6.3) ; extra == 'doc'
Requires-Dist: sympy (>=1.0) ; extra == 'doc'
Provides-Extra: examples
Requires-Dist: matplotlib (>=2.0) ; extra == 'examples'
Requires-Dist: sympy (>=1.0) ; extra == 'examples'
Provides-Extra: symbolic
Requires-Dist: sympy (>=1.0) ; extra == 'symbolic'
